ecoflow/__init__.py
ecoflow/common.py
ecoflow/delta2.py
ecoflow-0.2.dist-info/LICENSE
ecoflow-0.2.dist-info/WHEEL
ecoflow-0.2.dist-info/METADATA
ecoflow-0.2.dist-info/RECORD
