Metadata-Version: 2.1
Name: ecoflow
Version: 0.2
Summary: Python API for managing Ecoflow power stations
Author-email: Anton Ptashnik <iavtomator@gmail.com>
Requires-Python: >=3.5
Classifier: License :: OSI Approved :: MIT License
Requires-Dist: bleak >=0.20.2
Requires-Dist: pytest >= 7.3.0 ; extra == "test"
Requires-Dist: pytest-asyncio >= 0.21.0 ; extra == "test"
Project-URL: Home, https://github.com/anton-ptashnik/ecoflow-api-py
Provides-Extra: test
